{
  "Path": "Mods/GustavDev/Story/Dialogs/Act3/LowerCity/LOW_UnloadingTheBrigg_Dockworker_01.lsj",
  "UUID": "647b1cee-baf8-1563-5df4-c2d051a3eccc",
  "Category": "Generic NPC Dialog",
  "DefaultAddressedSpeakers": {
    "0": -1,
    "1": -1
  },
  "RootNodes": [
    "43e24025-90cb-fa9a-4db4-80fa7794b6db",
    "45640bdb-697b-a0c8-94dd-b798161a5f77"
  ],
  "Nodes": {
    "43e24025-90cb-fa9a-4db4-80fa7794b6db": {
      "UUID": "43e24025-90cb-fa9a-4db4-80fa7794b6db",
      "Constructor": "TagGreeting",
      "EndNode": true,
      "Root": true,
      "ShowOnce": false,
      "SpeakerNo": 0,
      "AddressedSpeaker": -1,
      "Children": [],
      "CheckFlags": [
        {
          "Flags": [
            {
              "UUID": "789d0498-2720-4271-a202-6eda196c5129",
              "value": false,
              "paramval": 1,
              "Name": "LOW_UnloadingTheBrigg_HasMet_Dockworker_01"
            }
          ],
          "Type": "Dialog"
        }
      ],
      "SetFlags": [
        {
          "Flags": [
            {
              "UUID": "789d0498-2720-4271-a202-6eda196c5129",
              "value": true,
              "paramval": 1,
              "Name": "LOW_UnloadingTheBrigg_HasMet_Dockworker_01"
            }
          ],
          "Type": "Dialog"
        }
      ],
      "TaggedTextList": [
        {
          "HasTagRule": false,
          "RuleGroup": {
            "TagCombineOp": 0,
            "Rules": [],
            "RuleString": ""
          },
          "TagTexts": [
            {
              "LineId": "5f670f65-b5ee-4b9f-ada9-d4685e3be42b",
              "Text": {
                "Handle": "h7e3da7dfgcf2cg436cgbdacg48d5dc37d587",
                "Value": "My last decent mate joined the Flaming Fists. Now I'm stuck with these two lugs. "
              }
            }
          ]
        }
      ],
      "EditorData": {
        "AnimationTags": "",
        "Attitude": "Default",
        "CinematicNodeContext": "",
        "CinematicObjects": "",
        "CustomCineArtKeysPresent": "False",
        "CustomLightingPresent": "False",
        "CustomSoundPresent": "False",
        "CustomVFXPresent": "False",
        "Emotion": "Default",
        "ForceDisableIsCustomNode": "False",
        "ID": "N1",
        "InternalNodeContext": "",
        "IsCustomNode": "False",
        "MusicTags": "",
        "NodeContext": "",
        "Quality": "Bronze",
        "SFXTags": "",
        "StateChangeTags": "",
        "TemplateNodeUUID": "00000000-0000-0000-0000-000000000000",
        "TemplateVersion": "0",
        "VFXTags": "",
        "collapsed": "False",
        "logicalname": "Greeting",
        "position": "15;15",
        "sourcetemplate": ""
      }
    },
    "45640bdb-697b-a0c8-94dd-b798161a5f77": {
      "UUID": "45640bdb-697b-a0c8-94dd-b798161a5f77",
      "Constructor": "TagGreeting",
      "EndNode": true,
      "Root": true,
      "ShowOnce": false,
      "SpeakerNo": 0,
      "AddressedSpeaker": -1,
      "Children": [],
      "CheckFlags": [
        {
          "Flags": [
            {
              "UUID": "789d0498-2720-4271-a202-6eda196c5129",
              "value": true,
              "paramval": 1,
              "Name": "LOW_UnloadingTheBrigg_HasMet_Dockworker_01"
            }
          ],
          "Type": "Dialog"
        }
      ],
      "SetFlags": [],
      "TaggedTextList": [
        {
          "HasTagRule": false,
          "RuleGroup": {
            "TagCombineOp": 0,
            "Rules": [],
            "RuleString": ""
          },
          "TagTexts": [
            {
              "LineId": "210521fa-4ca9-4f6b-90fe-b239e7332d8e",
              "Text": {
                "Handle": "h5b69296cg5966g4a1cgbdd1g18de4dc35976",
                "Value": "The dock's going to sink into the harbour before we get this tub unloaded."
              }
            }
          ]
        }
      ],
      "EditorData": {
        "AnimationTags": "",
        "Attitude": "Default",
        "CinematicNodeContext": "",
        "CinematicObjects": "",
        "CustomCineArtKeysPresent": "False",
        "CustomLightingPresent": "False",
        "CustomSoundPresent": "False",
        "CustomVFXPresent": "False",
        "Emotion": "Default",
        "ForceDisableIsCustomNode": "False",
        "ID": "N3",
        "InternalNodeContext": "",
        "IsCustomNode": "False",
        "MusicTags": "",
        "NodeContext": "",
        "Quality": "Bronze",
        "SFXTags": "",
        "StateChangeTags": "",
        "TemplateNodeUUID": "00000000-0000-0000-0000-000000000000",
        "TemplateVersion": "0",
        "VFXTags": "",
        "collapsed": "False",
        "logicalname": "Greeting - HasMet",
        "position": "15;234",
        "sourcetemplate": ""
      }
    }
  },
  "SpeakerDict": {
    "0": {
      "IsPeanutSpeaker": false,
      "SpeakerMappingId": "fba7a2c6-2c84-4ac6-839f-3ebf737c5dc2",
      "Index": 0,
      "List": [
        "8c7485ca-9105-425d-be85-2a4e39ef8c51"
      ],
      "SpeakerCharacter": {
        "DisplayName": "Bosun Sharley",
        "Type": "character",
        "MapKey": "8c7485ca-9105-425d-be85-2a4e39ef8c51",
        "Name": "S_LOW_UnloadingTheBrigg_Dockworker_01",
        "ParentTemplateId": null,
        "TemplateName": "7651267f-5eee-40c6-9b54-93a9772d3609"
      },
      "SpeakerGroupName": null
    },
    "1": {
      "IsPeanutSpeaker": false,
      "SpeakerMappingId": "d6f715b9-a342-48e3-ba1f-ed67e09850d1",
      "Index": 1,
      "List": [
        "e0d1ff71-04a8-4340-ae64-9684d846eb83"
      ],
      "SpeakerCharacter": {
        "DisplayName": "Player",
        "Type": "character",
        "MapKey": "e2badbf0-159a-4ef5-9e73-7bbeb3d1015a",
        "Name": "S_GLO_CharacterCreationDummy_001",
        "ParentTemplateId": null,
        "TemplateName": "fd7f2707-8f86-4836-bda8-e0db99c389cc"
      },
      "SpeakerGroupName": "GROUP_Players"
    }
  },
  "Synopsis": "Unloading the brigg vignette dockworker one-liner"
}